mdf_iter/mdf_iter.so
mdf_iter/mdf_iter.pyi
mdf_iter/__init__.py
mdf_iter/MessageTypes.py
mdf_iter-2.1.1.dist-info/METADATA
mdf_iter-2.1.1.dist-info/RECORD
mdf_iter-2.1.1.dist-info/WHEEL
mdf_iter-2.1.1.dist-info/licenses/LICENSE
