Metadata-Version: 2.1
Name: mdf_iter
Version: 2.1.1
Summary: Extract bus logging data from MDF4 files generated by CANedge from CSS Electronics
Project-URL: Homepage, https://www.csselectronics.com/pages/python-can-bus-api#void
Author-email: CSS Electronics <contact@csselectronics.com>
License-File: LICENSE
Classifier: License :: OSI Approved :: MIT License
Classifier: Operating System :: OS Independent
Classifier: Programming Language :: Python :: 3
Requires-Python: >=3.7
